usekit/.env.example
usekit/__init__.py
usekit/usemain.py
usekit/classes/__init__.py
usekit/classes/common/__init__.py
usekit/classes/common/errors/__init__.py
usekit/classes/common/errors/helper_debug.py
usekit/classes/common/errors/helper_errors.py
usekit/classes/common/errors/helper_safe.py
usekit/classes/common/errors/helper_setupdebug.py
usekit/classes/common/fileops/__init__.py
usekit/classes/common/fileops/helper_backup.py
usekit/classes/common/fileops/helper_diff.py
usekit/classes/common/fileops/helper_dotdict.py
usekit/classes/common/fileops/helper_dryrun.py
usekit/classes/common/fileops/helper_restore.py
usekit/classes/common/init/__init__.py
usekit/classes/common/init/helper_lazy.py
usekit/classes/common/init/helper_normalize.py
usekit/classes/common/init/helper_termux_storage.py
usekit/classes/common/keymap/__init__.py
usekit/classes/common/keymap/helper_keydata_path.py
usekit/classes/common/utils/__init__.py
usekit/classes/common/utils/helper_const.py
usekit/classes/common/utils/helper_const_line.py
usekit/classes/common/utils/helper_data_cache.py
usekit/classes/common/utils/helper_format.py
usekit/classes/common/utils/helper_keydata_path.py
usekit/classes/common/utils/helper_keypath.py
usekit/classes/common/utils/helper_parse_pattern.py
usekit/classes/common/utils/helper_path.py
usekit/classes/common/utils/helper_path_cache.py
usekit/classes/common/utils/helper_search.py
usekit/classes/common/utils/helper_timer.py
usekit/classes/common/utils/helper_treecache.py
usekit/classes/core/__init__.py
usekit/classes/core/env/__init__.py
usekit/classes/core/env/class_env.py
usekit/classes/core/env/loader_base_path.py
usekit/classes/core/env/loader_env.py
usekit/classes/data/__init__.py
usekit/classes/data/class_data_io.py
usekit/classes/data/class_data_sp.py
usekit/classes/data/base/__init__.py
usekit/classes/data/base/init/__init__.py
usekit/classes/data/base/init/wrap/__init__.py
usekit/classes/data/base/init/wrap/any/__init__.py
usekit-0.1.26.dist-info/METADATA
usekit-0.1.26.dist-info/WHEEL
usekit-0.1.26.dist-info/top_level.txt
usekit-0.1.26.dist-info/RECORD
