Metadata-Version: 2.4
Name: usekit
Version: 0.1.26
Summary: Minimal input, auto path toolkit (mobile-first, Colab+Drive)
Home-page: https://github.com/ropnfop/usekit
Author: ropnfop
Author-email: withropnfop@gmail.com
Classifier: Development Status :: 3 - Alpha
Classifier: Intended Audience :: Developers
Classifier: Topic :: Software Development :: Libraries :: Python Modules
Classifier: License :: OSI Approved :: MIT License
Classifier: Programming Language :: Python :: 3
Classifier: Programming Language :: Python :: 3.8
Classifier: Programming Language :: Python :: 3.9
Classifier: Programming Language :: Python :: 3.10
Classifier: Programming Language :: Python :: 3.11
Classifier: Programming Language :: Python :: 3.12
Classifier: Operating System :: OS Independent
Classifier: Environment :: Console
Requires-Python: >=3.8
Provides-Extra: full
Requires-Dist: PyYAML>=5.1; extra == "full"
Requires-Dist: python-dotenv>=0.10.0; extra == "full"
Provides-Extra: dev
Requires-Dist: PyYAML>=5.1; extra == "dev"
Requires-Dist: python-dotenv>=0.10.0; extra == "dev"
Requires-Dist: pytest>=7.0; extra == "dev"
Requires-Dist: black>=22.0; extra == "dev"
Requires-Dist: flake8>=4.0; extra == "dev"
Dynamic: author
Dynamic: author-email
Dynamic: classifier
Dynamic: description
Dynamic: description-content-type
Dynamic: home-page
Dynamic: provides-extra
Dynamic: requires-python
Dynamic: summary
